mosparo_api_client/Client.py
mosparo_api_client/MosparoException.py
mosparo_api_client/RequestHelper.py
mosparo_api_client/StatisticResult.py
mosparo_api_client/VerificationResult.py
mosparo_api_client/__init__.py
mosparo_api_client-1.1.2.dist-info/LICENSE
mosparo_api_client-1.1.2.dist-info/METADATA
mosparo_api_client-1.1.2.dist-info/WHEEL
mosparo_api_client-1.1.2.dist-info/top_level.txt
mosparo_api_client-1.1.2.dist-info/RECORD
