Metadata-Version: 2.1
Name: mosparo_api_client
Version: 1.1.2
Summary: Python API Client to communicate with mosparo.
Author-email: mosparo Core Developers <info@mosparo.io>
License: The MIT License (MIT)
Project-URL: Website, https://mosparo.io
Project-URL: GitHub, https://github.com/mosparo/python-api-client
Keywords: mosparo,api-client,spam-protection,accessibility,captcha
Classifier: Development Status :: 5 - Production/Stable
Classifier: Intended Audience :: Developers
Classifier: License :: OSI Approved :: MIT License
Classifier: Operating System :: OS Independent
Classifier: Programming Language :: Python :: 3.5
Classifier: Programming Language :: Python :: 3.6
Classifier: Programming Language :: Python :: 3.7
Classifier: Programming Language :: Python :: 3.8
Classifier: Programming Language :: Python :: 3.9
Classifier: Programming Language :: Python :: 3.10
Classifier: Programming Language :: Python :: 3.11
Classifier: Programming Language :: Python :: 3.12
Classifier: Topic :: Internet
Requires-Python: >=3.5
License-File: LICENSE
Requires-Dist: requests>=2.32.0
Provides-Extra: dev
Requires-Dist: pytest-runner; extra == "dev"
Requires-Dist: requests-mock; extra == "dev"
Requires-Dist: pip-tools; extra == "dev"
